reahl/componentmetadata/__init__.py
reahl/componentmetadata/setuptools.py
reahl_component_metadata-7.0.3.dist-info/METADATA
reahl_component_metadata-7.0.3.dist-info/WHEEL
reahl_component_metadata-7.0.3.dist-info/entry_points.txt
reahl_component_metadata-7.0.3.dist-info/top_level.txt
reahl_component_metadata-7.0.3.dist-info/RECORD
